MANIFEST.in
README.md
setup.cfg
setup.py
python_vpic.egg-info/PKG-INFO
python_vpic.egg-info/SOURCES.txt
python_vpic.egg-info/dependency_links.txt
python_vpic.egg-info/requires.txt
python_vpic.egg-info/top_level.txt
python_vpic.egg-info/zip-safe
vpic/__init__.py
vpic/models.py