Metadata-Version: 1.0
Name: python-vpic
Version: 0.1.5
Summary: Simple wrapper to the vPic API.
Home-page: https://github.com/OmniRisk/python-vpic
Author: Damian Hites
Author-email: damian@omnirisk.co
License: MIT
Keywords: vPic
Platform: UNKNOWN
